setup.py
bin/daisy-chain
daisychain/__init__.py
daisychain/constants.py
daisychain/decorators.py
daisychain/executor.py
daisychain/field.py
daisychain/importer.py
daisychain/instantiator.py
daisychain/log.py
daisychain/reference.py
daisychain/step.py
daisychain/step_status.py
daisychain.egg-info/PKG-INFO
daisychain.egg-info/SOURCES.txt
daisychain.egg-info/dependency_links.txt
daisychain.egg-info/requires.txt
daisychain.egg-info/top_level.txt
daisychain/steps/__init__.py
daisychain/steps/compiler.py
daisychain/steps/input.py
daisychain/steps/manual.py
daisychain/steps/marker.py
daisychain/steps/monitor.py
daisychain/steps/output.py
daisychain/steps/pipe.py
daisychain/steps/wait.py
daisychain/steps/authentication/__init__.py
daisychain/steps/authentication/basic_auth.py
daisychain/steps/compilers/__init__.py
daisychain/steps/compilers/chain.py
daisychain/steps/compilers/namespace_compiler.py
daisychain/steps/compilers/separate_dependency_tree.py
daisychain/steps/compilers/step_config_inheritance.py
daisychain/steps/inputs/__init__.py
daisychain/steps/inputs/file.py
daisychain/steps/inputs/system.py
daisychain/steps/outputs/__init__.py
daisychain/steps/outputs/file.py
daisychain/steps/outputs/system.py
daisychain/steps/pipes/__init__.py
daisychain/steps/pipes/json_convert.py
daisychain/steps/system/__init__.py
daisychain/steps/system/run_command.py
test/__init__.py
test/test_compilers__chain_compiler.py
test/test_compilers__namespace_compiler.py
test/test_compilers__separate_dependency_tree.py
test/test_compilers__step_config_inheritance.py
test/test_decorators.py
test/test_executor.py
test/test_field.py
test/test_importer.py
test/test_instantiator.py
test/test_monitor.py
test/test_pipes__json_convert.py
test/test_reference.py
test/test_step.py
test/test_step_status.py
test/test_steps__authentication__basic_auth.py
test/test_steps__input.py
test/test_steps__inputs__file.py
test/test_steps__inputs__stdin.py
test/test_steps__manual.py
test/test_steps__marker.py
test/test_steps__outputs_file.py
test/test_steps__outputs_system.py
test/test_steps__system__run_command.py
test/test_steps__wait.py
test/util.py
test/mock_requests/__init__.py
