Metadata-Version: 1.0
Name: daisychain
Version: 0.1.1
Summary: Configuration-based OO-dependency resolution workflow engine
Home-page: https://github.com/python-daisychain/daisychain
Author: Jeff Edwards
Author-email: jeff@edwardsj.com
License: MIT License
Platform: UNKNOWN
